cli/__init__.py
cli/finops_cli.py
cli/cost_calculator/__init__.py
cli/cost_calculator/calculator.py
cli/cost_calculator/exporter.py
cli/cost_calculator/reporter.py
cli/models/__init__.py
cli/models/cost_models.py
cli/models/ec2.py
cli/models/pricing.py
cli/services/__init__.py
cli/services/exceptions.py
cli/services/price_calculator.py
cli/services/aws/__init__.py
cli/services/aws/ec2.py
cli/services/aws/pricing.py
cli/ui/__init__.py
cli/ui/colors.py
cli/ui/reporter.py
cli/utils/__init__.py
cli/utils/csv_exporter.py
finops_cli-0.1.3.dist-info/licenses/LICENSE
finops_cli-0.1.3.dist-info/METADATA
finops_cli-0.1.3.dist-info/WHEEL
finops_cli-0.1.3.dist-info/entry_points.txt
finops_cli-0.1.3.dist-info/top_level.txt
finops_cli-0.1.3.dist-info/RECORD
